onedevcommongoogleservices/Gmail.py
onedevcommongoogleservices/GoogleCalendar.py
onedevcommongoogleservices/GoogleCloudStorage.py
onedevcommongoogleservices/GoogleDrive.py
onedevcommongoogleservices/GooglePubSub.py
onedevcommongoogleservices/GoogleServicesAuth.py
onedevcommongoogleservices/TokenStore.py
onedevcommongoogleservices-0.1.2.dist-info/METADATA
onedevcommongoogleservices-0.1.2.dist-info/WHEEL
onedevcommongoogleservices-0.1.2.dist-info/RECORD
