Metadata-Version: 2.3
Name: onedevcommongoogleservices
Version: 0.1.2
Summary: Ferramenta para integração com o Google Services
Author: renan.cardeal@ufly.com.br
Requires-Python: >=3.13
Classifier: Programming Language :: Python :: 3
Classifier: Programming Language :: Python :: 3.13
Requires-Dist: google-api-python-client (>=2.179.0,<3.0.0)
Requires-Dist: google-auth-httplib2 (>=0.2.0,<0.3.0)
Requires-Dist: google-auth-oauthlib (>=1.2.2,<2.0.0)
Requires-Dist: google-cloud-pubsub (>=2.31.1,<3.0.0)
Requires-Dist: google-cloud-storage (>=3.3.0,<4.0.0)
Requires-Dist: pytz (>=2025.2,<2026.0)
